datalad_cds/__init__.py
datalad_cds/_version.py
datalad_cds/cds_remote.py
datalad_cds/compat.py
datalad_cds/download_cds.py
datalad_cds/git_annex_backend_XGRIBNORMV1.py
datalad_cds/spec.py
datalad_cds-0.0.13.dist-info/licenses/LICENSE
datalad_cds-0.0.13.dist-info/METADATA
datalad_cds-0.0.13.dist-info/WHEEL
datalad_cds-0.0.13.dist-info/entry_points.txt
datalad_cds-0.0.13.dist-info/top_level.txt
datalad_cds-0.0.13.dist-info/RECORD
