Metadata-Version: 2.4
Name: datalad-cds
Version: 0.0.13
Summary: DataLad extension for downloading from the Copernicus Climate Data Store
Author: Matthias Riße
Author-email: The DataLad Team and Contributors <team@datalad.org>, Benedikt Bulich <b.bulich@fz-juelich.de>, Daniel Klauß <daniel.klauss@alumni.fh-aachen.de>, Laurens Jan van Haaren <l.van.haaren@fz-juelich.de>, Matthias Riße <m.risse@fz-juelich.de>
Maintainer-email: Matthias Riße <m.risse@fz-juelich.de>
License: # Main Copyright/License
Project-URL: repository, https://github.com/matrss/datalad-cds
Classifier: Programming Language :: Python
Classifier: License :: OSI Approved :: MIT License
Classifier: Programming Language :: Python :: 3
Requires-Python: >=3.10
License-File: LICENSE
Requires-Dist: datalad>=0.17.0
Requires-Dist: annexremote>=1.6.0
Requires-Dist: cdsapi>=0.5.1
Provides-Extra: devel
Requires-Dist: coverage; extra == "devel"
Requires-Dist: hypothesis; extra == "devel"
Requires-Dist: mypy; extra == "devel"
Requires-Dist: pytest; extra == "devel"
Requires-Dist: pytest-cov; extra == "devel"
Requires-Dist: ruff; extra == "devel"
Requires-Dist: sphinx; extra == "devel"
Requires-Dist: sphinx_rtd_theme; extra == "devel"
Dynamic: license-file
